README.rst
setup.py
src/osinfo/__init__.py
src/osinfo/osinfo.py
src/python_osinfo.egg-info/PKG-INFO
src/python_osinfo.egg-info/SOURCES.txt
src/python_osinfo.egg-info/dependency_links.txt
src/python_osinfo.egg-info/not-zip-safe
src/python_osinfo.egg-info/top_level.txt