Metadata-Version: 1.1
Name: python_osinfo
Version: 0.2.0
Summary: Python OS information retriever.
Home-page: https://github.com/Dalveen84/python-osinfo/
Author: Rodrigo Núñez Mujica
Author-email: rnunezmujica@icloud.com
License: UNKNOWN
Platform: UNKNOWN
Classifier: Development Status :: 4 - Beta
Classifier: Intended Audience :: Developers
Classifier: License :: OSI Approved :: GNU General Public License v3 (GPLv3)
Classifier: Operating System :: OS Independent
Classifier: Programming Language :: Python :: 2.7
Classifier: Programming Language :: Python :: Implementation :: CPython
Classifier: Topic :: System :: Operating System
Classifier: Topic :: Software Development :: Libraries :: Python Modules
